mwmodal/__init__.py
mwmodal/mw_modal.py
mwmodal/tools.py
MorletWaveModal-0.6.3.dist-info/LICENSE
MorletWaveModal-0.6.3.dist-info/METADATA
MorletWaveModal-0.6.3.dist-info/WHEEL
MorletWaveModal-0.6.3.dist-info/top_level.txt
MorletWaveModal-0.6.3.dist-info/RECORD
