Metadata-Version: 2.1
Name: MorletWaveModal
Version: 0.6.3
Summary: Morlet Wave Modal Identification.
Home-page: https://github.com/ladisk/MorletWaveModal
Author: Ivan Tomac, Janko Slavič
Author-email: ivan.tomac@fs.uni-lj.si, janko.slavic@fs.uni-lj.si
Maintainer: Ivan Tomac, Janko Slavič
Maintainer-email: janko.slavic@fs.uni-lj.si
License: MIT license
Keywords: modal parameters, morlet-wave, identification
Classifier: Development Status :: 3 - Alpha
Classifier: Intended Audience :: Developers
Classifier: Programming Language :: Python :: 3.9
License-File: LICENSE
Requires-Dist: numpy
Requires-Dist: scipy
Requires-Dist: mwdi (==0.72)
Requires-Dist: pylint
Requires-Dist: pytest
